setup.py
codebase/__init__.py
codebase/client.py
codebase_api.egg-info/PKG-INFO
codebase_api.egg-info/SOURCES.txt
codebase_api.egg-info/dependency_links.txt
codebase_api.egg-info/requires.txt
codebase_api.egg-info/top_level.txt