Metadata-Version: 1.1
Name: codebase-api
Version: 0.1.1
Summary: Wrapper library for connecting with CasebaseHQ API
Home-page: https://github.com/pyriku/codebase-python
Author: Pablo Recio
Author-email: pablo@recio.me
License: BSD
Keywords: codebase api wrapper
Platform: UNKNOWN
Classifier: Development Status :: 3 - Alpha
Classifier: Environment :: Web Environment
Classifier: Intended Audience :: Developers
Classifier: License :: OSI Approved :: BSD License
Classifier: Operating System :: OS Independent
Classifier: Programming Language :: Python
Classifier: Topic :: Internet :: WWW/HTTP
